Metadata-Version: 1.0
Name: gaussian-binomial-calculator
Version: 0.1
Summary: Gaussian and Binomial distributions calculator
Home-page: UNKNOWN
Author: Danilo Salazar
Author-email: danilo@origo.ec
License: UNKNOWN
Platform: UNKNOWN
